sagda/__init__.py
sagda/api_utils.py
sagda/data_augmentation.py
sagda/data_generation.py
sagda/data_validation.py
sagda/utils.py
sagda-0.1.1.dist-info/LICENSE
sagda-0.1.1.dist-info/METADATA
sagda-0.1.1.dist-info/WHEEL
sagda-0.1.1.dist-info/top_level.txt
sagda-0.1.1.dist-info/RECORD
