Metadata-Version: 2.1
Name: sagda
Version: 0.1.1
Summary: Generating and Augmenting Agricultural Synthetic Data in Africa
Home-page: https://github.com/PySAGDA/sagda/
Author: PySAGDA
Author-email: abdelghani.belgaid@um6p.ma
Classifier: Programming Language :: Python :: 3
Classifier: License :: OSI Approved :: MIT License
Classifier: Operating System :: OS Independent
Requires-Python: >=3.6
License-File: LICENSE
Requires-Dist: pandas
Requires-Dist: numpy
Requires-Dist: scikit-learn
Requires-Dist: tensorflow
Requires-Dist: requests
